sallie/__init__.py
sallie/__main__.py
sallie/__version__.py
sallie/cli_main.py
sallie/next_tvdb.py
sallie/tv_next.py
sallie-0.6.10.dist-info/LICENSE
sallie-0.6.10.dist-info/METADATA
sallie-0.6.10.dist-info/WHEEL
sallie-0.6.10.dist-info/entry_points.txt
sallie-0.6.10.dist-info/top_level.txt
sallie-0.6.10.dist-info/RECORD
