Metadata-Version: 2.1
Name: sallie
Version: 0.6.10
Summary: TV episodes checker
Home-page: https://github.com/the01/python-sallie
Author: the01
Author-email: jungflor@gmail.com
License: MIT License
Keywords: sallie tv shows tvdb
Platform: UNKNOWN
Classifier: Development Status :: 5 - Production/Stable
Classifier: Intended Audience :: Developers
Classifier: Natural Language :: English
Classifier: License :: OSI Approved :: MIT License
Classifier: Operating System :: Unix
Classifier: Operating System :: POSIX
Classifier: Operating System :: Microsoft :: Windows
Classifier: Programming Language :: Python
Classifier: Programming Language :: Python :: 3
Classifier: Programming Language :: Python :: 3.6
Classifier: Programming Language :: Python :: 3.7
Classifier: Programming Language :: Python :: 3.8
Classifier: Programming Language :: Python :: Implementation :: CPython
Requires-Python: >=3.6
Requires-Dist: flotils (<0.6.0,>=0.4)
Requires-Dist: pytz (>=2016.4)
Requires-Dist: tvdb-api (<4.0,>=3.0)
Requires-Dist: future (<0.16,>=0.15.2)
Requires-Dist: python-dateutil
